zenith/__init__.py
zenith/__version__.py
zenith/app.py
zenith/background.py
zenith/cli.py
zenith/decorators.py
zenith/exceptions.py
zenith/logging.py
zenith/pagination.py
zenith/auth/__init__.py
zenith/auth/config.py
zenith/auth/dependencies.py
zenith/auth/jwt.py
zenith/auth/password.py
zenith/core/__init__.py
zenith/core/application.py
zenith/core/auto_config.py
zenith/core/config.py
zenith/core/container.py
zenith/core/dependencies.py
zenith/core/json_encoder.py
zenith/core/patterns.py
zenith/core/routing.py
zenith/core/scoped.py
zenith/core/service.py
zenith/core/supervisor.py
zenith/core/routing/__init__.py
zenith/core/routing/dependencies.py
zenith/core/routing/dependency_resolver.py
zenith/core/routing/executor.py
zenith/core/routing/response_processor.py
zenith/core/routing/router.py
zenith/core/routing/specs.py
zenith/core/routing/utils.py
zenith/db/__init__.py
zenith/db/async_engine.py
zenith/db/migrations.py
zenith/db/models.py
zenith/db/sqlmodel.py
zenith/db/tracing.py
zenith/dev/__init__.py
zenith/dev/generators/__init__.py
zenith/dev/generators/api.py
zenith/dev/generators/base.py
zenith/dev/generators/model.py
zenith/dev/generators/service.py
zenith/dev/generators/utils.py
zenith/exceptions/config.py
zenith/http/__init__.py
zenith/http/client.py
zenith/jobs/__init__.py
zenith/jobs/manager.py
zenith/jobs/queue.py
zenith/jobs/scheduler.py
zenith/jobs/worker.py
zenith/middleware/__init__.py
zenith/middleware/auth.py
zenith/middleware/cache.py
zenith/middleware/compression.py
zenith/middleware/cors.py
zenith/middleware/csrf.py
zenith/middleware/exceptions.py
zenith/middleware/logging.py
zenith/middleware/rate_limit.py
zenith/middleware/request_id.py
zenith/middleware/security.py
zenith/middleware/websocket.py
zenith/mixins/__init__.py
zenith/mixins/docs.py
zenith/mixins/middleware.py
zenith/mixins/routing.py
zenith/mixins/services.py
zenith/monitoring/__init__.py
zenith/monitoring/health.py
zenith/monitoring/metrics.py
zenith/monitoring/performance.py
zenithweb-0.0.14.dist-info/METADATA
zenithweb-0.0.14.dist-info/WHEEL
zenithweb-0.0.14.dist-info/entry_points.txt
zenithweb-0.0.14.dist-info/licenses/LICENSE
zenithweb-0.0.14.dist-info/RECORD
