Metadata-Version: 2.4
Name: zenithweb
Version: 0.0.14
Summary: Modern Python web framework for building APIs with minimal boilerplate
Project-URL: Homepage, https://github.com/nijaru/zenith
Project-URL: Documentation, https://nijaru.github.io/zenith
Project-URL: Repository, https://github.com/nijaru/zenith.git
Project-URL: Issues, https://github.com/nijaru/zenith/issues
Author-email: Nick Russo <nijaru7@gmail.com>
License: MIT
License-File: LICENSE
Keywords: api,async,database,framework,performance,web,websockets
Classifier: Development Status :: 4 - Beta
Classifier: Intended Audience :: Developers
Classifier: License :: OSI Approved :: MIT License
Classifier: Programming Language :: Python :: 3
Classifier: Programming Language :: Python :: 3.12
Classifier: Programming Language :: Python :: 3.13
Classifier: Programming Language :: Python :: 3.14
Classifier: Topic :: Internet :: WWW/HTTP :: Dynamic Content
Classifier: Topic :: Software Development :: Libraries :: Application Frameworks
Requires-Python: <3.15,>=3.12
Requires-Dist: aiosqlite>=0.19.0
Requires-Dist: alembic>=1.17.0
Requires-Dist: asyncpg>=0.31.0
Requires-Dist: click>=8.1.0
Requires-Dist: greenlet>=3.2.4
Requires-Dist: jinja2>=3.1.0
Requires-Dist: msgspec>=0.19.0
Requires-Dist: orjson>=3.11.3
Requires-Dist: prometheus-client>=0.22.1
Requires-Dist: psutil>=7.0.0
Requires-Dist: pwdlib[argon2]>=0.2.1
Requires-Dist: pydantic!=2.12.1,>=2.12.0
Requires-Dist: pyjwt>=2.8.0
Requires-Dist: python-multipart>=0.0.6
Requires-Dist: redis>=5.0.0
Requires-Dist: sqlalchemy>=2.0.44
Requires-Dist: sqlmodel>=0.0.27
Requires-Dist: starlette>=0.32.0
Requires-Dist: structlog>=23.0.0
Requires-Dist: uvicorn[standard]>=0.24.0
Requires-Dist: uvloop>=0.21.0
Requires-Dist: websockets>=12.0
Provides-Extra: ai
Requires-Dist: anthropic>=0.40.0; extra == 'ai'
Requires-Dist: httpx-sse>=0.4.0; extra == 'ai'
Requires-Dist: openai>=1.0.0; extra == 'ai'
Provides-Extra: benchmark
Requires-Dist: aiosqlite>=0.19.0; extra == 'benchmark'
Requires-Dist: fastapi>=0.104.0; extra == 'benchmark'
Requires-Dist: flask-sqlalchemy>=3.1.0; extra == 'benchmark'
Requires-Dist: flask>=3.0.0; extra == 'benchmark'
Requires-Dist: httpx>=0.25.0; extra == 'benchmark'
Requires-Dist: psutil>=5.9.0; extra == 'benchmark'
Provides-Extra: compression
Requires-Dist: brotli>=1.1.0; extra == 'compression'
Requires-Dist: zstandard>=0.23.0; extra == 'compression'
Provides-Extra: dev
Requires-Dist: httpx>=0.25.0; extra == 'dev'
Requires-Dist: ipdb>=0.13.0; extra == 'dev'
Requires-Dist: pytest-asyncio>=0.21.0; extra == 'dev'
Requires-Dist: pytest-cov>=4.1.0; extra == 'dev'
Requires-Dist: pytest>=7.4.0; extra == 'dev'
Requires-Dist: ruff>=0.1.6; extra == 'dev'
Provides-Extra: graphql
Requires-Dist: strawberry-graphql[cli]>=0.284.0; extra == 'graphql'
Provides-Extra: http3
Requires-Dist: aioquic>=1.2.0; extra == 'http3'
Requires-Dist: cryptography>=42.0.0; extra == 'http3'
Provides-Extra: mcp
Requires-Dist: mcp>=1.0.0; extra == 'mcp'
Provides-Extra: performance
Provides-Extra: tracing
Requires-Dist: opentelemetry-distro>=0.59b0; extra == 'tracing'
Requires-Dist: opentelemetry-instrumentation-fastapi>=0.59b0; extra == 'tracing'
